xyf_mcp_demo/__init__.py
xyf_mcp_demo-0.1.0.dist-info/WHEEL
xyf_mcp_demo-0.1.0.dist-info/entry_points.txt
xyf_mcp_demo-0.1.0.dist-info/METADATA
xyf_mcp_demo-0.1.0.dist-info/RECORD
