Metadata-Version: 2.3
Name: xyf-mcp-demo
Version: 0.1.0
Summary: Add your description here
Author: 司马青衫
Author-email: 司马青衫 <974871455@qq.com>
Requires-Dist: mcp[cli]>=1.13.1
Requires-Python: >=3.13
